{
  "countries": [
    {
      "id": 1,
      "name": "Israel",
      "abbr": "il",
      "vote": 0,
      "alteration": 0
    },
    {
      "id": 2,
      "name": "Poland",
      "abbr": "pl",
      "vote": 0,
      "alteration": 0
    },
    {
      "id": 3,
      "name": "Belarus",
      "abbr": "by",
      "vote": 0,
      "alteration": 0
    },
    {
      "id": 4,
      "name": "Austria",
      "abbr": "at",
      "vote": 0,
      "alteration": 0
    },
    {
      "id": 5,
      "name": "Armenia",
      "abbr": "am",
      "vote": 0,
      "alteration": 0
    },
    {
      "id": 6,
      "name": "The Netherlands",
      "abbr": "nl",
      "vote": 0,
      "alteration": 0
    },
    {
      "id": 7,
      "name": "Moldova",
      "abbr": "md",
      "vote": 0,
      "alteration": 0
    },
    {
      "id": 8,
      "name": "Hungary",
      "abbr": "hu",
      "vote": 0,
      "alteration": 0
    },
    {
      "id": 9,
      "name": "Italy",
      "abbr": "it",
      "vote": 0,
      "alteration": 0
    },
    {
      "id": 10,
      "name": "Denmark",
      "abbr": "dk",
      "vote": 0,
      "alteration": 0
    },
    {
      "id": 11,
      "name": "Portugal",
      "abbr": "pt",
      "vote": 0,
      "alteration": 0
    },
    {
      "id": 12,
      "name": "Azerbaijan",
      "abbr": "az",
      "vote": 0,
      "alteration": 0
    },
    {
      "id": 13,
      "name": "Croatia",
      "abbr": "hr",
      "vote": 0,
      "alteration": 0
    },
    {
      "id": 14,
      "name": "Australia",
      "abbr": "au",
      "vote": 0,
      "alteration": 0
    },
    {
      "id": 15,
      "name": "Greece",
      "abbr": "gr",
      "vote": 0,
      "alteration": 0
    },
    {
      "id": 16,
      "name": "Spain",
      "abbr": "es",
      "vote": 0,
      "alteration": 0
    },
    {
      "id": 17,
      "name": "Norway",
      "abbr": "no",
      "vote": 0,
      "alteration": 0
    },
    {
      "id": 18,
      "name": "United Kingdom",
      "abbr": "gb",
      "vote": 0,
      "alteration": 0
    },
    {
      "id": 19,
      "name": "Cyprus",
      "abbr": "cy",
      "vote": 0,
      "alteration": 0
    },
    {
      "id": 20,
      "name": "Romania",
      "abbr": "ro",
      "vote": 0,
      "alteration": 0
    },
    {
      "id": 21,
      "name": "Germany",
      "abbr": "de",
      "vote": 0,
      "alteration": 0
    },
    {
      "id": 22,
      "name": "Ukraine",
      "abbr": "ua",
      "vote": 0,
      "alteration": 0
    },
    {
      "id": 23,
      "name": "Belgium",
      "abbr": "be",
      "vote": 0,
      "alteration": 0
    },
    {
      "id": 24,
      "name": "Sweden",
      "abbr": "se",
      "vote": 0,
      "alteration": 0
    },
    {
      "id": 25,
      "name": "Bulgaria",
      "abbr": "bg",
      "vote": 0,
      "alteration": 0
    },
    {
      "id": 26,
      "name": "France",
      "abbr": "fr",
      "vote": 0,
      "alteration": 0
    }
  ]
}
